byteboss/__init__.py
byteboss/const.py
byteboss/util.py
byteboss/resource/__init__.py
byteboss/resource/control_lora.py
byteboss/resource/fcs.py
byteboss/resource/kandinsky.py
byteboss/resource/mg.py
byteboss/resource/sd_loras.py
byteboss/resource/sdxl.py
byteboss/resource/whisper.py
byteboss/resource/engines/__init__.py
byteboss/resource/engines/engine.py
byteboss-0.0.8.dist-info/METADATA
byteboss-0.0.8.dist-info/WHEEL
byteboss-0.0.8.dist-info/top_level.txt
byteboss-0.0.8.dist-info/RECORD
