Metadata-Version: 2.1
Name: byteboss
Version: 0.0.8
Summary: Test
Author: zenafey
Author-email: zenafey@eugw.ru
License: MIT
Requires-Dist: requests
Requires-Dist: colorama
Requires-Dist: aiohttp
